arctic/__init__.py
arctic/_cache.py
arctic/_compression.py
arctic/_config.py
arctic/_util.py
arctic/arctic.py
arctic/auth.py
arctic/decorators.py
arctic/exceptions.py
arctic/hooks.py
arctic/hosts.py
arctic/multi_index.py
arctic/asynchronous/__init__.py
arctic/asynchronous/_workers_pool.py
arctic/asynchronous/async_arctic.py
arctic/asynchronous/async_utils.py
arctic/chunkstore/__init__.py
arctic/chunkstore/_chunker.py
arctic/chunkstore/chunkstore.py
arctic/chunkstore/date_chunker.py
arctic/chunkstore/passthrough_chunker.py
arctic/chunkstore/utils.py
arctic/chunkstore/tools/__init__.py
arctic/chunkstore/tools/tools.py
arctic/date/__init__.py
arctic/date/_daterange.py
arctic/date/_generalslice.py
arctic/date/_mktz.py
arctic/date/_parse.py
arctic/date/_util.py
arctic/fixtures/__init__.py
arctic/fixtures/arctic.py
arctic/scripts/__init__.py
arctic/scripts/arctic_copy_data.py
arctic/scripts/arctic_create_user.py
arctic/scripts/arctic_delete_library.py
arctic/scripts/arctic_enable_sharding.py
arctic/scripts/arctic_fsck.py
arctic/scripts/arctic_init_library.py
arctic/scripts/arctic_list_libraries.py
arctic/scripts/arctic_prune_versions.py
arctic/scripts/utils.py
arctic/serialization/__init__.py
arctic/serialization/_serializer.py
arctic/serialization/incremental.py
arctic/serialization/numpy_arrays.py
arctic/serialization/numpy_records.py
arctic/store/__init__.py
arctic/store/_ndarray_store.py
arctic/store/_pandas_ndarray_store.py
arctic/store/_pickle_store.py
arctic/store/_version_store_utils.py
arctic/store/audit.py
arctic/store/bitemporal_store.py
arctic/store/bson_store.py
arctic/store/metadata_store.py
arctic/store/version_store.py
arctic/store/versioned_item.py
arctic/tickstore/__init__.py
arctic/tickstore/tickstore.py
arctic/tickstore/toplevel.py
arctic_latest-1.75.0.dist-info/METADATA
arctic_latest-1.75.0.dist-info/RECORD
arctic_latest-1.75.0.dist-info/WHEEL
arctic_latest-1.75.0.dist-info/entry_points.txt
arctic_latest-1.75.0.dist-info/top_level.txt
