Metadata-Version: 2.1
Name: arctic-latest
Version: 1.75.0
Summary: AHL Research Versioned TimeSeries and Tick store. We are publishing the latest version of it.
Home-page: https://github.com/manahl/arctic
Author: Man AHL Technology
Author-email: ManAHLTech@ahl.com
License: GPL
Keywords: ahl,keyvalue,tickstore,mongo,timeseries
Platform: UNKNOWN
Classifier: Development Status :: 4 - Beta
Classifier: License :: OSI Approved :: GNU Library or Lesser General Public License (LGPL)
Classifier: Programming Language :: Python :: 2.7
Classifier: Programming Language :: Python :: 3.4
Classifier: Programming Language :: Python :: 3.5
Classifier: Programming Language :: Python :: 3.6
Classifier: Programming Language :: Python :: Implementation :: CPython
Classifier: Operating System :: POSIX
Classifier: Operating System :: MacOS
Classifier: Operating System :: Microsoft :: Windows
Classifier: Topic :: Database
Classifier: Topic :: Database :: Front-Ends
Classifier: Topic :: Software Development :: Libraries
Requires-Dist: decorator
Requires-Dist: enum-compat
Requires-Dist: mockextras
Requires-Dist: pandas
Requires-Dist: pymongo (>=3.6.0)
Requires-Dist: python-dateutil
Requires-Dist: pytz
Requires-Dist: tzlocal
Requires-Dist: lz4
Requires-Dist: futures; python_version == "2.7"
